salesforce_report_fetcher/__init__.py
salesforce_report_fetcher/fetcher.py
salesforce_report_fetcher/version.py
sf_report_fetcher-0.1.0.dist-info/LICENSE
sf_report_fetcher-0.1.0.dist-info/METADATA
sf_report_fetcher-0.1.0.dist-info/WHEEL
sf_report_fetcher-0.1.0.dist-info/top_level.txt
sf_report_fetcher-0.1.0.dist-info/RECORD
