Metadata-Version: 2.2
Name: sf-report-fetcher
Version: 0.1.0
Summary: A Python utility to fetch complete Salesforce reports, bypassing the 2000-row limit. Supports custom API versions.
Author-email: Your Name <your.email@example.com>
License: MIT License
Project-URL: Homepage, https://github.com/hardiksondagar/sf-report-fetcher
Project-URL: Documentation, https://github.com/hardiksondagar/sf-report-fetcher#readme
Project-URL: Repository, https://github.com/hardiksondagar/sf-report-fetcher.git
Project-URL: Issues, https://github.com/hardiksondagar/sf-report-fetcher/issues
Keywords: salesforce,report,api,pagination,salesforce-api
Classifier: License :: OSI Approved :: MIT License
Classifier: Programming Language :: Python
Classifier: Programming Language :: Python :: 3
Classifier: Programming Language :: Python :: 3.7
Classifier: Programming Language :: Python :: 3.8
Classifier: Programming Language :: Python :: 3.9
Classifier: Programming Language :: Python :: 3.10
Classifier: Programming Language :: Python :: 3.11
Classifier: Development Status :: 4 - Beta
Classifier: Intended Audience :: Developers
Classifier: Topic :: Software Development :: Libraries :: Python Modules
Classifier: Topic :: Internet :: WWW/HTTP
Requires-Python: >=3.7
License-File: LICENSE
Requires-Dist: requests<3.0.0,>=2.22.0
Dynamic: requires-python
